compute_tf_idf_vectors/__init__.py
compute_tf_idf_vectors/cli.py
compute_tf_idf_vectors-1.0.3.202208310829.dist-info/AUTHORS
compute_tf_idf_vectors-1.0.3.202208310829.dist-info/LICENSE
compute_tf_idf_vectors-1.0.3.202208310829.dist-info/METADATA
compute_tf_idf_vectors-1.0.3.202208310829.dist-info/WHEEL
compute_tf_idf_vectors-1.0.3.202208310829.dist-info/entry_points.txt
compute_tf_idf_vectors-1.0.3.202208310829.dist-info/top_level.txt
compute_tf_idf_vectors-1.0.3.202208310829.dist-info/RECORD
