Metadata-Version: 2.1
Name: compute-tf-idf-vectors
Version: 1.0.3.202208310829
Summary: Utility to compute sparse TF-IDF vector representation for dataset in the document_tracking_resources format based on a feature file.
Home-page: https://gitlab.univ-lr.fr/cross-lingual-event-tracking/datasets/dataset_manipulation_tools/compute_tf_idf_weights
Author: Guillaume Bernard
Author-email: contact@guillaume-bernard.fr
License: UNKNOWN
Project-URL: Bug Tracker, https://gitlab.univ-lr.fr/cross-lingual-event-tracking/datasets/dataset_manipulation_tools/compute_tf_idf_weights/-/issues
Platform: UNKNOWN
Classifier: Programming Language :: Python :: 3.9
Classifier: License :: OSI Approved :: GNU General Public License v3 (GPLv3)
Classifier: Operating System :: POSIX :: Linux
Classifier: Topic :: Scientific/Engineering :: Artificial Intelligence
Classifier: Intended Audience :: Science/Research
Requires-Python: >=3.9
License-File: LICENSE
License-File: AUTHORS
Requires-Dist: pandas (~=1.3.5)
Requires-Dist: scikit-learn (~=1.0.2)
Requires-Dist: tqdm (~=4.62.3)
Requires-Dist: numpy (~=1.19.5)
Requires-Dist: scipy (~=1.7.3)
Requires-Dist: document-processing (~=1.0.0)
Requires-Dist: document-tracking-resources (~=1.0.0)
